{
  "recentFiles": [
    {
      "basename": "readme",
      "path": "20-Chunzhao/C-CV_Interview/通用计算机视觉算法面经/C++与操作系统等面试题/操作系统/readme.md"
    },
    {
      "basename": "孤儿进程和僵尸进程的区别",
      "path": "20-Chunzhao/C-CV_Interview/通用计算机视觉算法面经/C++与操作系统等面试题/操作系统/孤儿进程和僵尸进程的区别.md"
    },
    {
      "basename": "递归锁",
      "path": "20-Chunzhao/C-CV_Interview/通用计算机视觉算法面经/C++与操作系统等面试题/操作系统/递归锁.md"
    },
    {
      "basename": "IO复用的原理",
      "path": "20-Chunzhao/C-CV_Interview/通用计算机视觉算法面经/C++与操作系统等面试题/操作系统/IO复用的原理.md"
    },
    {
      "basename": "进程的创建过程",
      "path": "20-Chunzhao/C-CV_Interview/通用计算机视觉算法面经/C++与操作系统等面试题/操作系统/进程的创建过程.md"
    },
    {
      "basename": "函数调⽤和系统调⽤的区别",
      "path": "20-Chunzhao/C-CV_Interview/通用计算机视觉算法面经/C++与操作系统等面试题/操作系统/函数调⽤和系统调⽤的区别.md"
    },
    {
      "basename": "进程创建子进程",
      "path": "20-Chunzhao/C-CV_Interview/通用计算机视觉算法面经/C++与操作系统等面试题/操作系统/进程创建子进程.md"
    },
    {
      "basename": "常⻅的IO模型",
      "path": "20-Chunzhao/C-CV_Interview/通用计算机视觉算法面经/C++与操作系统等面试题/操作系统/常⻅的IO模型.md"
    },
    {
      "basename": "1",
      "path": "20-Chunzhao/C-CV_Interview/通用计算机视觉算法面经/C++与操作系统等面试题/C++面经题/1.md"
    },
    {
      "basename": "readme",
      "path": "20-Chunzhao/C-CV_Interview/通用计算机视觉算法面经/Python面试题/readme.md"
    }
  ],
  "omittedPaths": [],
  "maxLength": 10,
  "openType": "tab"
}